cdktf_cdktf_provider_cloudflare/__init__.py
cdktf_cdktf_provider_cloudflare/py.typed
cdktf_cdktf_provider_cloudflare/_jsii/__init__.py
cdktf_cdktf_provider_cloudflare/_jsii/provider-cloudflare@13.6.0.jsii.tgz
cdktf_cdktf_provider_cloudflare/access_rule/__init__.py
cdktf_cdktf_provider_cloudflare/account/__init__.py
cdktf_cdktf_provider_cloudflare/account_dns_settings/__init__.py
cdktf_cdktf_provider_cloudflare/account_dns_settings_internal_view/__init__.py
cdktf_cdktf_provider_cloudflare/account_member/__init__.py
cdktf_cdktf_provider_cloudflare/account_subscription/__init__.py
cdktf_cdktf_provider_cloudflare/account_token/__init__.py
cdktf_cdktf_provider_cloudflare/address_map/__init__.py
cdktf_cdktf_provider_cloudflare/api_shield/__init__.py
cdktf_cdktf_provider_cloudflare/api_shield_discovery_operation/__init__.py
cdktf_cdktf_provider_cloudflare/api_shield_operation/__init__.py
cdktf_cdktf_provider_cloudflare/api_shield_operation_schema_validation_settings/__init__.py
cdktf_cdktf_provider_cloudflare/api_shield_schema/__init__.py
cdktf_cdktf_provider_cloudflare/api_shield_schema_validation_settings/__init__.py
cdktf_cdktf_provider_cloudflare/api_token/__init__.py
cdktf_cdktf_provider_cloudflare/argo_smart_routing/__init__.py
cdktf_cdktf_provider_cloudflare/argo_tiered_caching/__init__.py
cdktf_cdktf_provider_cloudflare/authenticated_origin_pulls/__init__.py
cdktf_cdktf_provider_cloudflare/authenticated_origin_pulls_certificate/__init__.py
cdktf_cdktf_provider_cloudflare/authenticated_origin_pulls_settings/__init__.py
cdktf_cdktf_provider_cloudflare/bot_management/__init__.py
cdktf_cdktf_provider_cloudflare/byo_ip_prefix/__init__.py
cdktf_cdktf_provider_cloudflare/calls_sfu_app/__init__.py
cdktf_cdktf_provider_cloudflare/calls_turn_app/__init__.py
cdktf_cdktf_provider_cloudflare/certificate_pack/__init__.py
cdktf_cdktf_provider_cloudflare/cloud_connector_rules/__init__.py
cdktf_cdktf_provider_cloudflare/cloudforce_one_request/__init__.py
cdktf_cdktf_provider_cloudflare-13.6.0.dist-info/LICENSE
cdktf_cdktf_provider_cloudflare-13.6.0.dist-info/METADATA
cdktf_cdktf_provider_cloudflare-13.6.0.dist-info/WHEEL
cdktf_cdktf_provider_cloudflare-13.6.0.dist-info/top_level.txt
cdktf_cdktf_provider_cloudflare-13.6.0.dist-info/RECORD
